gpl_maths/__init__.py
gpl_maths/maths.py
gpl_maths-0.2.dist-info/METADATA
gpl_maths-0.2.dist-info/WHEEL
gpl_maths-0.2.dist-info/top_level.txt
gpl_maths-0.2.dist-info/RECORD
